ember/__init__.py
ember/feature_extraction.py
ember/features.py
ember_cdd_wdis-1.2.1.dist-info/LICENSE.txt
ember_cdd_wdis-1.2.1.dist-info/METADATA
ember_cdd_wdis-1.2.1.dist-info/WHEEL
ember_cdd_wdis-1.2.1.dist-info/RECORD
