Metadata-Version: 2.3
Name: EMBER_CDD__Wdis
Version: 1.2.1
Summary: Elastic Malware Benchmark for Empowering Researchers 
License: MIT
Author: Luca Fabri
Author-email: luca.fabri1999@gmail.com
Requires-Python: >=3.10,<4.0
Classifier: License :: OSI Approved :: MIT License
Classifier: Programming Language :: Python :: 3
Classifier: Programming Language :: Python :: 3.10
Classifier: Programming Language :: Python :: 3.11
Classifier: Programming Language :: Python :: 3.12
Classifier: Programming Language :: Python :: 3.13
Requires-Dist: coverage (>=7.8.0,<8.0.0)
Requires-Dist: lightgbm (>=4.6.0,<5.0.0)
Requires-Dist: mypy (>=1.15.0,<2.0.0)
Requires-Dist: numpy (>=2.0.0,<3.0.0)
Requires-Dist: pandas (>=2.0,<3.0)
Requires-Dist: pefile (>=2024.8.26,<2025.0.0)
Requires-Dist: polars (>=1.8.2,<2.0.0)
Requires-Dist: pytest (>=8.3.5,<9.0.0)
Requires-Dist: ruff (>=0.11.6,<0.12.0)
Requires-Dist: scikit-learn (>=1.6.1,<2.0.0)
Requires-Dist: signify (>=0.7.1,<0.8.0)
Requires-Dist: tqdm (>=4.0,<5.0)
